dataverse_sdk/__init__.py
dataverse_sdk/client.py
dataverse_sdk/connections.py
dataverse_sdk/constants.py
dataverse_sdk/apis/__init__.py
dataverse_sdk/apis/backend.py
dataverse_sdk/apis/third_party.py
dataverse_sdk/exceptions/__init__.py
dataverse_sdk/exceptions/client.py
dataverse_sdk/export/__init__.py
dataverse_sdk/export/base.py
dataverse_sdk/export/coco.py
dataverse_sdk/export/constant.py
dataverse_sdk/export/exporter.py
dataverse_sdk/export/utils.py
dataverse_sdk/export/visionai.py
dataverse_sdk/export/vqa.py
dataverse_sdk/export/yolo.py
dataverse_sdk/schemas/__init__.py
dataverse_sdk/schemas/api.py
dataverse_sdk/schemas/client.py
dataverse_sdk/schemas/common.py
dataverse_sdk/schemas/format.py
dataverse_sdk/utils/__init__.py
dataverse_sdk/utils/utils.py
dataverse_sdk-2.5.1.dist-info/METADATA
dataverse_sdk-2.5.1.dist-info/WHEEL
dataverse_sdk-2.5.1.dist-info/top_level.txt
dataverse_sdk-2.5.1.dist-info/RECORD
