Metadata-Version: 2.4
Name: dataverse-sdk
Version: 2.5.1
Summary: Dataverse SDK For Python
Home-page: 
Author: LinkerVision
Classifier: Programming Language :: Python :: 3
Requires-Python: >=3.10, <4
Requires-Dist: pydantic==2.*
Requires-Dist: requests
Requires-Dist: httpx>=0.23.0
Requires-Dist: tqdm
Requires-Dist: aiofiles
Requires-Dist: visionai-data-format==2.0.0
Requires-Dist: aiohttp
Requires-Dist: aiohttp_retry
Requires-Dist: numpy<2,>=1.21
Requires-Dist: opencv-contrib-python==4.8.1.78
Dynamic: author
Dynamic: classifier
Dynamic: description
Dynamic: description-content-type
Dynamic: requires-dist
Dynamic: requires-python
Dynamic: summary
